databend_sqlalchemy/__init__.py
databend_sqlalchemy/connector.py
databend_sqlalchemy/databend_dialect.py
databend_sqlalchemy/dml.py
databend_sqlalchemy/errors.py
databend_sqlalchemy/provision.py
databend_sqlalchemy/requirements.py
databend_sqlalchemy/types.py
databend_sqlalchemy-0.5.2.dist-info/licenses/LICENSE
databend_sqlalchemy-0.5.2.dist-info/METADATA
databend_sqlalchemy-0.5.2.dist-info/WHEEL
databend_sqlalchemy-0.5.2.dist-info/entry_points.txt
databend_sqlalchemy-0.5.2.dist-info/top_level.txt
databend_sqlalchemy-0.5.2.dist-info/RECORD
