Metadata-Version: 2.4
Name: databend_sqlalchemy
Version: 0.5.2
Summary: Sqlalchemy adapter for Databend
Home-page: https://github.com/databendlabs/databend-sqlalchemy
Author: Databend Cloud
Author-email: hanshanjie@databend.com
License: Apache-2.0
Project-URL: Bug Tracker, https://github.com/databendlabs/databend-sqlalchemy
Classifier: License :: OSI Approved :: Apache Software License
Classifier: License :: OSI Approved :: MIT License
Classifier: Operating System :: OS Independent
Classifier: Programming Language :: Python :: 3
Classifier: Programming Language :: Python :: 3 :: Only
Classifier: Programming Language :: Python :: 3.7
Classifier: Programming Language :: Python :: 3.8
Classifier: Programming Language :: Python :: 3.9
Classifier: Programming Language :: Python :: 3.10
Classifier: Programming Language :: Python :: 3.11
Classifier: Programming Language :: Python :: 3.12
Requires-Python: >=3.8
License-File: LICENSE
Requires-Dist: databend-driver>=0.26.2
Requires-Dist: sqlalchemy>=1.4
Provides-Extra: dev
Requires-Dist: devtools==0.7.0; extra == "dev"
Requires-Dist: mock==4.0.3; extra == "dev"
Requires-Dist: pre-commit==2.15.0; extra == "dev"
Requires-Dist: pytest==8.1.1; extra == "dev"
Requires-Dist: pytest-cov==3.0.0; extra == "dev"
Requires-Dist: pytest-xdist==3.5.0; extra == "dev"
Requires-Dist: sqlalchemy-stubs==0.4; extra == "dev"
Provides-Extra: superset
Requires-Dist: apache_superset>=1.4.1; extra == "superset"
Dynamic: license-file
